trace_that_route/__init__.py
trace_that_route/traceroute.py
trace_that_route-0.0.2.dist-info/licenses/LICENSE.md
trace_that_route-0.0.2.dist-info/METADATA
trace_that_route-0.0.2.dist-info/WHEEL
trace_that_route-0.0.2.dist-info/top_level.txt
trace_that_route-0.0.2.dist-info/RECORD
