Metadata-Version: 2.4
Name: trace-that-route
Version: 0.0.2
Summary: Simple python script adding a wrapper around the traceroute command.
Author: LeStegii
License-Expression: MIT
Project-URL: Homepage, https://github.com/LeStegii/trace-that-route
Project-URL: Issues, https://github.com/LeStegii/trace-that-route/issues
Keywords: traceroute,network,ip,python
Classifier: Programming Language :: Python :: 3
Classifier: Operating System :: POSIX :: Linux
Requires-Python: >=3.7
License-File: LICENSE.md
Dynamic: license-file
